airsqlmodel/__init__.py
airsqlmodel/main.py
airsqlmodel-0.1.4.dist-info/WHEEL
airsqlmodel-0.1.4.dist-info/METADATA
airsqlmodel-0.1.4.dist-info/RECORD
