Metadata-Version: 2.3
Name: airsqlmodel
Version: 0.1.4
Summary: Air + SQLModel made easy!
Author: Daniel Roy Greenfeld
Author-email: Daniel Roy Greenfeld <daniel@feldroy.com>
Requires-Dist: air>=0.39.0
Requires-Dist: greenlet>=3.2.4
Requires-Dist: sqlmodel>=0.0.27
Requires-Dist: asyncpg>=0.30.0 ; extra == 'postgresql'
Requires-Dist: psycopg-binary>=3.2.12 ; extra == 'postgresql'
Requires-Dist: aiosqlite>=0.21.0 ; extra == 'sqlite'
Requires-Python: >=3.13
Project-URL: Homepage, https://github.com/pydanny/airsqlmodel
Project-URL: Issues, https://github.com/pydanny/airsqlmodel/issues
Provides-Extra: postgresql
Provides-Extra: sqlite
